mapof/allocations/__init__.py
mapof/allocations/essentials.py
mapof/allocations/core/__init__.py
mapof/allocations/core/alloctask.py
mapof/allocations/core/alloctasklibrarian.py
mapof/allocations/core/experiment.py
mapof/allocations/core/logs.py
mapof/allocations/core/pot.py
mapof/allocations/cultures/approval_dirichlet.py
mapof/allocations/cultures/basic_cultures.py
mapof/allocations/cultures/converter.py
mapof/allocations/cultures/euclidean.py
mapof/allocations/cultures/misc.py
mapof/allocations/cultures/paths.py
mapof/allocations/cultures/tools.py
mapof/allocations/features/basic_features.py
mapof/allocations/features/or_tools_features/envy_features.py
mapof/allocations/features/or_tools_features/feature_data.py
mapof/allocations/features/or_tools_features/helpers.py
mapof/allocations/features/or_tools_features/maximin_feature.py
mapof/allocations/features/or_tools_features/nash_welfare_feature.py
mapof/allocations/features/or_tools_features/prop_share.py
mapof/allocations/features/or_tools_features/social_welfare_feature.py
mapof/allocations/features/or_tools_features/wrapper.py
mapof/allocations/metrics/__init__.py
mapof/allocations/metrics/abs_soc_dist.py
mapof/allocations/metrics/fastdist.py
mapof/allocations/metrics/features_singles_dist.py
mapof/allocations/metrics/idealdist.py
mapof/allocations/metrics/rrobin.py
mapof/allocations/metrics/surveying.py
mapof_allocations-0.1.0b1.dist-info/licenses/LICENSE.txt
mapof_allocations-0.1.0b1.dist-info/METADATA
mapof_allocations-0.1.0b1.dist-info/WHEEL
mapof_allocations-0.1.0b1.dist-info/top_level.txt
mapof_allocations-0.1.0b1.dist-info/RECORD
