Metadata-Version: 2.4
Name: mapof-allocations
Version: 0.1.0b1
Summary: Map of Allocations
Author-email: Paula Böhm <paulaboehm14@gmail.com>, Paul Gölz <mail@paulgoelz.de>, Andrzej Kaczmarczyk <andrzej.kaczmarczyk@agh.edu.pl>, Stanisław Szufa <s.szufa@gmail.com>
Maintainer-email: Andrzej Kaczmarczyk <andrzej.kaczmarczyk@agh.edu.pl>, Stanisław Szufa <s.szufa@gmail.com>
License: MIT License
Classifier: Programming Language :: Python :: 3
Classifier: License :: OSI Approved :: MIT License
Classifier: Operating System :: OS Independent
Requires-Python: >=3.10
License-File: LICENSE.txt
Requires-Dist: mapof
Requires-Dist: mapof-elections
Requires-Dist: ortools>=9.5
Requires-Dist: colorama>=0.4
Dynamic: license-file
